[
  {
    "Name":"IMS",
    "DBaaS":"no",
    "License":"Commercial",
    "Website":"http://www.ibm.com/software/data/ims/ims/",
    "Details":"http://db-engines.com/en/system/IMS",
    "Type":"Navigational DBMS",
    "Score":1.51,
    "Size":152
  },
  {
    "Name":"IDMS",
    "DBaaS":"no",
    "License":"Commercial",
    "Website":"www.ca.com/足us/足products/足detail/足CA-IDMS.aspx",
    "Details":"http://db-engines.com/en/system/IDMS",
    "Type":"Navigational DBMS",
    "Score":1.37,
    "Size":138
  }
]
